typex/__init__.py
typex/decorator.py
typex/traits_extension.py
typex/typing_extensions.py
typex/validation.py
python_typex-0.0.2.dist-info/AUTHORS.rst
python_typex-0.0.2.dist-info/METADATA
python_typex-0.0.2.dist-info/WHEEL
python_typex-0.0.2.dist-info/top_level.txt
python_typex-0.0.2.dist-info/RECORD
