Metadata-Version: 2.1
Name: python-typex
Version: 0.0.2
Author-email: typex developers <antoine.grigis@cea.fr>
License: CECILL-B
Project-URL: Source, https://github.com/neurospin-deppinsight/typex
Project-URL: Tracker, https://github.com/neurospin-deppinsight/typex/issues
Platform: Linux
Platform: OSX
Classifier: Environment :: Console
Classifier: Operating System :: OS Independent
Classifier: Programming Language :: Python :: 3
Classifier: Topic :: Scientific/Engineering
Requires-Python: >=3.9
License-File: AUTHORS.rst
Requires-Dist: torch <2.8.0,>=2.1.0
Requires-Dist: traits
